README.md
setup.cfg
setup.py
src/keepfresh/__init__.py
src/keepfresh/command_line.py
src/keepfresh/event.py
src/keepfresh/observer.py
src/keepfresh/restart_handler.py
src/keepfresh.egg-info/PKG-INFO
src/keepfresh.egg-info/SOURCES.txt
src/keepfresh.egg-info/dependency_links.txt
src/keepfresh.egg-info/entry_points.txt
src/keepfresh.egg-info/top_level.txt