Metadata-Version: 2.1
Name: keepfresh
Version: 0.0.4
Summary: Filesystem event polling
Home-page: https://github.com/reritom/KeepFresh
Author: Tomas Sheers
Author-email: t.sheers@outlook.com
License: UNKNOWN
Download-URL: https://github.com/reritom/KeepFresh/archive/v0.0.4.tar.gz
Keywords: FILESYSTEM,EVENT,POLLING
Platform: UNKNOWN
